hnapi/__init__.py
hnapi/api_connector.py
hnapi/hnapi.py
hnapi/hnitem.py
hnapi/connectors/__init__.py
hnapi/connectors/api_connector.py
hnapi/items/__init__.py
hnapi/items/commentitem.py
hnapi/items/hnitem.py
hnapi/items/pollitem.py
hnapi/items/storyitem.py
hnapi/items/updatesitem.py
hnapi/items/useritem.py
hnapi/schemas/__init__.py
hnapi/schemas/commentschema.py
hnapi/schemas/field.py
hnapi/schemas/pollschema.py
hnapi/schemas/schema.py
hnapi/schemas/storyschema.py
hnapi/schemas/updatesschema.py
hnapi/schemas/userschema.py
hntop-0.0.10.dist-info/DESCRIPTION.rst
hntop-0.0.10.dist-info/METADATA
hntop-0.0.10.dist-info/RECORD
hntop-0.0.10.dist-info/WHEEL
hntop-0.0.10.dist-info/metadata.json
hntop-0.0.10.dist-info/top_level.txt
