Metadata-Version: 2.0
Name: hntop
Version: 0.0.10
Summary: Python wrapper over HackerNews Firebase API
Home-page: https://github.com/rylans/hackernews-top
Author: Rylan Santinon
Author-email: rylans@gmail.com
License: Apache
Keywords: hn,hackernews,hnapi,hackernews top
Platform: UNKNOWN
Classifier: Development Status :: 3 - Alpha
Classifier: License :: OSI Approved :: Apache Software License
Classifier: Natural Language :: English
Classifier: Programming Language :: Python :: 2.6
Classifier: Programming Language :: Python :: 2.7
Classifier: Programming Language :: Python :: 3.3
Classifier: Programming Language :: Python :: 3.4
Classifier: Topic :: Utilities
Classifier: Topic :: Internet :: WWW/HTTP :: Indexing/Search
